{
    "欧元": {
        "rate": "758.41",
        "updateTime": "2025.02.04 16:33:52"
    },
    "英镑": {
        "rate": "912.01",
        "updateTime": "2025.02.04 16:33:52"
    },
    "日元": {
        "rate": "4.7298",
        "updateTime": "2025.02.04 16:33:52"
    },
    "韩国元": {
        "rate": "0.5063",
        "updateTime": "2025.02.04 16:33:52"
    },
    "新加坡元": {
        "rate": "541.1",
        "updateTime": "2025.02.04 16:33:52"
    },
    "美元": {
        "rate": "733.08",
        "updateTime": "2025.02.04 16:33:52"
    }
}