{
    "欧元": {
        "rate": "788.87",
        "updateTime": "2025.03.31 13:52:26"
    },
    "英镑": {
        "rate": "943.52",
        "updateTime": "2025.03.31 13:52:26"
    },
    "日元": {
        "rate": "4.8868",
        "updateTime": "2025.03.31 13:52:26"
    },
    "韩国元": {
        "rate": "0.4978",
        "updateTime": "2025.03.31 13:52:26"
    },
    "新加坡元": {
        "rate": "543.23",
        "updateTime": "2025.03.31 13:52:26"
    },
    "美元": {
        "rate": "726.92",
        "updateTime": "2025.03.31 13:52:26"
    }
}