{
    "欧元": {
        "rate": "810.72",
        "updateTime": "2025.05.19 07:05:15"
    },
    "英镑": {
        "rate": "963.46",
        "updateTime": "2025.05.19 07:05:15"
    },
    "日元": {
        "rate": "4.9912",
        "updateTime": "2025.05.19 07:05:15"
    },
    "韩国元": {
        "rate": "0.521",
        "updateTime": "2025.05.19 07:05:15"
    },
    "新加坡元": {
        "rate": "558.02",
        "updateTime": "2025.05.19 07:05:15"
    },
    "美元": {
        "rate": "723.36",
        "updateTime": "2025.05.19 07:05:15"
    }
}