{
    "欧元": {
        "rate": "822.75",
        "updateTime": "2025.05.08 11:56:44"
    },
    "英镑": {
        "rate": "969.42",
        "updateTime": "2025.05.08 11:56:44"
    },
    "日元": {
        "rate": "5.0575",
        "updateTime": "2025.05.08 11:56:44"
    },
    "韩国元": {
        "rate": "0.5246",
        "updateTime": "2025.05.08 11:56:44"
    },
    "新加坡元": {
        "rate": "561.27",
        "updateTime": "2025.05.08 11:56:44"
    },
    "美元": {
        "rate": "725.21",
        "updateTime": "2025.05.08 11:56:44"
    }
}