{
    "欧元": {
        "rate": "845.66",
        "updateTime": "2025.09.17 11:56:20"
    },
    "英镑": {
        "rate": "973.65",
        "updateTime": "2025.09.17 11:56:20"
    },
    "日元": {
        "rate": "4.8692",
        "updateTime": "2025.09.17 11:56:20"
    },
    "韩国元": {
        "rate": "0.5182",
        "updateTime": "2025.09.17 11:56:20"
    },
    "新加坡元": {
        "rate": "559.02",
        "updateTime": "2025.09.17 11:56:20"
    },
    "美元": {
        "rate": "712.56",
        "updateTime": "2025.09.17 11:56:20"
    }
}