{
    "欧元": {
        "rate": "789.51",
        "updateTime": "2025.03.11 11:49:40"
    },
    "英镑": {
        "rate": "937.89",
        "updateTime": "2025.03.11 11:49:40"
    },
    "日元": {
        "rate": "4.9458",
        "updateTime": "2025.03.11 11:49:40"
    },
    "韩国元": {
        "rate": "0.5021",
        "updateTime": "2025.03.11 11:49:40"
    },
    "新加坡元": {
        "rate": "545.78",
        "updateTime": "2025.03.11 11:49:40"
    },
    "美元": {
        "rate": "726.57",
        "updateTime": "2025.03.11 11:49:40"
    }
}