{
    "欧元": {
        "rate": "831.43",
        "updateTime": "2025.07.29 21:52:01"
    },
    "英镑": {
        "rate": "959.75",
        "updateTime": "2025.07.29 21:52:01"
    },
    "日元": {
        "rate": "4.8506",
        "updateTime": "2025.07.29 21:52:01"
    },
    "韩国元": {
        "rate": "0.5206",
        "updateTime": "2025.07.29 21:52:01"
    },
    "新加坡元": {
        "rate": "559.25",
        "updateTime": "2025.07.29 21:52:01"
    },
    "美元": {
        "rate": "719.65",
        "updateTime": "2025.07.29 21:52:01"
    }
}