{
    "欧元": {
        "rate": "835.49",
        "updateTime": "2025.08.26 15:56:00"
    },
    "英镑": {
        "rate": "967.47",
        "updateTime": "2025.08.26 15:56:00"
    },
    "日元": {
        "rate": "4.867",
        "updateTime": "2025.08.26 15:56:00"
    },
    "韩国元": {
        "rate": "0.5156",
        "updateTime": "2025.08.26 15:56:00"
    },
    "新加坡元": {
        "rate": "559.14",
        "updateTime": "2025.08.26 15:56:00"
    },
    "美元": {
        "rate": "718",
        "updateTime": "2025.08.26 15:56:00"
    }
}