{
    "欧元": {
        "rate": "838.18",
        "updateTime": "2025.08.11 21:12:58"
    },
    "英镑": {
        "rate": "968.34",
        "updateTime": "2025.08.11 21:12:58"
    },
    "日元": {
        "rate": "4.879",
        "updateTime": "2025.08.11 21:12:58"
    },
    "韩国元": {
        "rate": "0.5193",
        "updateTime": "2025.08.11 21:12:58"
    },
    "新加坡元": {
        "rate": "560.84",
        "updateTime": "2025.08.11 21:12:58"
    },
    "美元": {
        "rate": "720.25",
        "updateTime": "2025.08.11 21:12:58"
    }
}