{
    "欧元": {
        "rate": "805.04",
        "updateTime": "2025.04.08 17:46:25"
    },
    "英镑": {
        "rate": "938.92",
        "updateTime": "2025.04.08 17:46:25"
    },
    "日元": {
        "rate": "5.0004",
        "updateTime": "2025.04.08 17:46:25"
    },
    "韩国元": {
        "rate": "0.5008",
        "updateTime": "2025.04.08 17:46:25"
    },
    "新加坡元": {
        "rate": "545.43",
        "updateTime": "2025.04.08 17:46:25"
    },
    "美元": {
        "rate": "735.64",
        "updateTime": "2025.04.08 17:46:25"
    }
}