{
    "欧元": {
        "rate": "760.57",
        "updateTime": "2025.01.29 11:48:45"
    },
    "英镑": {
        "rate": "907.27",
        "updateTime": "2025.01.29 11:48:45"
    },
    "日元": {
        "rate": "4.69",
        "updateTime": "2025.01.29 11:48:45"
    },
    "韩国元": {
        "rate": "0.5074",
        "updateTime": "2025.01.29 11:48:45"
    },
    "新加坡元": {
        "rate": "540.05",
        "updateTime": "2025.01.29 11:48:45"
    },
    "美元": {
        "rate": "727.57",
        "updateTime": "2025.01.29 11:48:45"
    }
}